phasr/__init__.py
phasr/__main__.py
phasr/config.py
phasr/py.typed
phasr/cross_section_fitter/__init__.py
phasr/cross_section_fitter/data_prepper.py
phasr/cross_section_fitter/fit_initializer.py
phasr/cross_section_fitter/fit_organizer.py
phasr/cross_section_fitter/fit_performer.py
phasr/cross_section_fitter/illustrator.py
phasr/cross_section_fitter/parameters.py
phasr/cross_section_fitter/pickler.py
phasr/cross_section_fitter/statistical_measures.py
phasr/cross_section_fitter/uncertainties.py
phasr/dirac_solvers/__init__.py
phasr/dirac_solvers/base.py
phasr/dirac_solvers/boundstate.py
phasr/dirac_solvers/continuumstate.py
phasr/dirac_solvers/post_processing/__init__.py
phasr/dirac_solvers/post_processing/crosssection.py
phasr/dirac_solvers/post_processing/left_right_asymmetry.py
phasr/dirac_solvers/post_processing/overlap_integrals.py
phasr/nuclei/__init__.py
phasr/nuclei/base.py
phasr/nuclei/references.py
phasr/nuclei/selector.py
phasr/nuclei/data/info.txt
phasr/nuclei/data/params_FB.txt
phasr/nuclei/data/params_SOG.txt
phasr/nuclei/data/params_basic.txt
phasr/nuclei/parameterizations/__init__.py
phasr/nuclei/parameterizations/basic.py
phasr/nuclei/parameterizations/coulomb.py
phasr/nuclei/parameterizations/fermi.py
phasr/nuclei/parameterizations/fourier_bessel.py
phasr/nuclei/parameterizations/numerical.py
phasr/nuclei/parameterizations/oszillator_basis.py
phasr/physical_constants/__init__.py
phasr/physical_constants/constants.py
phasr/physical_constants/iaea_nds.py
phasr/physical_constants/pdg.py
phasr/physical_constants/data/info.txt
phasr/physical_constants/data/mass_width_2021.mcd
phasr/physical_constants/data/nuclei_2022.csv
phasr/utility/__init__.py
phasr/utility/basis_change.py
phasr/utility/continuer.py
phasr/utility/math.py
phasr/utility/mpsentinel.py
phasr/utility/spliner.py
phasr-0.5.1.dist-info/METADATA
phasr-0.5.1.dist-info/WHEEL
phasr-0.5.1.dist-info/licenses/LICENSE
phasr-0.5.1.dist-info/RECORD
