Metadata-Version: 2.4
Name: phasr
Version: 0.5.1
Summary: Package to calculate scattering phase shifts for arbitrary radial potentials using the phase shift method as well as resulting crosssections as mainly used in the context of elastic electron nucleus scattering.
Project-URL: homepage, https://github.com/Partynumbers42/phasr
Project-URL: repository, https://github.com/Partynumbers42/phasr
Author-email: Frederic Noël <noel@ipt.unibe.ch>
License: BSD-3-Clause
License-File: LICENSE
Classifier: Development Status :: 3 - Alpha
Classifier: License :: OSI Approved :: BSD License
Classifier: Programming Language :: Python :: 3
Classifier: Programming Language :: Python :: 3.8
Classifier: Programming Language :: Python :: 3.9
Classifier: Programming Language :: Python :: 3.10
Classifier: Programming Language :: Python :: 3.11
Classifier: Programming Language :: Python :: 3.12
Classifier: Programming Language :: Python :: 3.13
Classifier: Typing :: Typed
Requires-Python: >=3.8
Requires-Dist: mpmath
Requires-Dist: numdifftools
Requires-Dist: numpy
Requires-Dist: scipy
Provides-Extra: dev
Requires-Dist: ipython; extra == 'dev'
Requires-Dist: mypy; extra == 'dev'
Requires-Dist: pdbpp; extra == 'dev'
Requires-Dist: pre-commit; extra == 'dev'
Requires-Dist: rich; extra == 'dev'
Requires-Dist: ruff; extra == 'dev'
Provides-Extra: test
Requires-Dist: pytest; extra == 'test'
Requires-Dist: pytest-cov; extra == 'test'
